deepmark/__init__.py
deepmark/detect.py
deepmark/embed.py
deepmark-1.0.0.dist-info/METADATA
deepmark-1.0.0.dist-info/WHEEL
deepmark-1.0.0.dist-info/top_level.txt
deepmark-1.0.0.dist-info/RECORD
