Metadata-Version: 2.4
Name: deepmark
Version: 1.0.0
Summary: deepmark: Model-agnostic, robust, and compliance-ready text watermarking library for LLMs and content platforms.
Home-page: https://github.com/yourusername/deepmark
Author: Your Name
Author-email: your@email.com
Classifier: Programming Language :: Python :: 3
Classifier: License :: OSI Approved :: MIT License
Classifier: Operating System :: OS Independent
Classifier: Intended Audience :: Developers
Classifier: Topic :: Software Development :: Libraries :: Python Modules
Requires-Python: >=3.7
Requires-Dist: spacy
Requires-Dist: nltk
Requires-Dist: cryptography
Requires-Dist: click
Requires-Dist: pydantic
Requires-Dist: requests
Requires-Dist: numpy
Dynamic: author
Dynamic: author-email
Dynamic: classifier
Dynamic: description
Dynamic: description-content-type
Dynamic: home-page
Dynamic: requires-dist
Dynamic: requires-python
Dynamic: summary
